huangjb_numpy/__init__.py
huangjb_numpy/_lib_build/numpy/__config__.py
huangjb_numpy/_lib_build/numpy/__config__.pyi
huangjb_numpy/_lib_build/numpy/__init__.cython-30.pxd
huangjb_numpy/_lib_build/numpy/__init__.pxd
huangjb_numpy/_lib_build/numpy/__init__.py
huangjb_numpy/_lib_build/numpy/__init__.pyi
huangjb_numpy/_lib_build/numpy/_array_api_info.py
huangjb_numpy/_lib_build/numpy/_array_api_info.pyi
huangjb_numpy/_lib_build/numpy/_configtool.py
huangjb_numpy/_lib_build/numpy/_configtool.pyi
huangjb_numpy/_lib_build/numpy/_distributor_init.py
huangjb_numpy/_lib_build/numpy/_distributor_init.pyi
huangjb_numpy/_lib_build/numpy/_expired_attrs_2_0.py
huangjb_numpy/_lib_build/numpy/_expired_attrs_2_0.pyi
huangjb_numpy/_lib_build/numpy/_globals.py
huangjb_numpy/_lib_build/numpy/_globals.pyi
huangjb_numpy/_lib_build/numpy/_pytesttester.py
huangjb_numpy/_lib_build/numpy/_pytesttester.pyi
huangjb_numpy/_lib_build/numpy/conftest.py
huangjb_numpy/_lib_build/numpy/dtypes.py
huangjb_numpy/_lib_build/numpy/dtypes.pyi
huangjb_numpy/_lib_build/numpy/exceptions.py
huangjb_numpy/_lib_build/numpy/exceptions.pyi
huangjb_numpy/_lib_build/numpy/matlib.py
huangjb_numpy/_lib_build/numpy/matlib.pyi
huangjb_numpy/_lib_build/numpy/py.typed
huangjb_numpy/_lib_build/numpy/version.py
huangjb_numpy/_lib_build/numpy/version.pyi
huangjb_numpy/_lib_build/numpy/__pycache__/__config__.cpython-313.pyc
huangjb_numpy/_lib_build/numpy/__pycache__/__init__.cpython-313.pyc
huangjb_numpy/_lib_build/numpy/__pycache__/_array_api_info.cpython-313.pyc
huangjb_numpy/_lib_build/numpy/__pycache__/_configtool.cpython-313.pyc
huangjb_numpy/_lib_build/numpy/__pycache__/_distributor_init.cpython-313.pyc
huangjb_numpy/_lib_build/numpy/__pycache__/_expired_attrs_2_0.cpython-313.pyc
huangjb_numpy/_lib_build/numpy/__pycache__/_globals.cpython-313.pyc
huangjb_numpy/_lib_build/numpy/__pycache__/_pytesttester.cpython-313.pyc
huangjb_numpy/_lib_build/numpy/__pycache__/conftest.cpython-313.pyc
huangjb_numpy-3.3.1.dist-info/METADATA
huangjb_numpy-3.3.1.dist-info/WHEEL
huangjb_numpy-3.3.1.dist-info/top_level.txt
huangjb_numpy-3.3.1.dist-info/RECORD
